README.md
setup.py
SynologyAPI/__init__.py
SynologyAPI/__main__.py
SynologyAPI/auth.py
SynologyAPI/filestation.py
SynologyAPI.egg-info/PKG-INFO
SynologyAPI.egg-info/SOURCES.txt
SynologyAPI.egg-info/dependency_links.txt
SynologyAPI.egg-info/entry_points.txt
SynologyAPI.egg-info/not-zip-safe
SynologyAPI.egg-info/requires.txt
SynologyAPI.egg-info/top_level.txt
test/test_FileStation.py
test/test_auth.py