Metadata-Version: 2.1
Name: SynologyAPI
Version: 0.0.4
Summary: A simple wrapper for some of the functions that the Synology API supports.
Home-page: https://github.com/Marist-SDN-SecureCloud/SynologyAPI
License: MIT
Platform: UNKNOWN
